mly/SRD.py
mly/__init__.py
mly/_version.py
mly/createFileSystem.py
mly/exceptions.py
mly/offlinefar.py
mly/plugins.py
mly/projectwave.py
mly/simulateddetectornoise.py
mly/skymap_utils.py
mly/tools.py
mly/validators.py
mly/waveforms.py
mly/datatools/__init__.py
mly/datatools/core.py
mly/datatools/datatools.py
mly/datatools/generator.py
mly/datatools/tests/__init__.py
mly/datatools/tests/test_core.py
mly/datatools/tests/test_datatools.py
mly/datatools/tests/test_generator.py
mly/tests/README.md
mly/tests/__init__.py
mly/tests/test_init.py
mly/tests/test_tools.py
mly-1.1.0.dist-info/LICENSE
mly-1.1.0.dist-info/METADATA
mly-1.1.0.dist-info/WHEEL
mly-1.1.0.dist-info/top_level.txt
mly-1.1.0.dist-info/RECORD
